{
  "play_market": {
    "no-NO": [
      "no"
    ],
    "en-US": [
      "us"
    ],
    "en-GB": [
      "gb"
    ],
    "en-CA": [
      "ca"
    ],
    "en-AU": [
      "au"
    ],
    "en-IN": [
      "in"
    ],
    "en-ZA": [
      "za"
    ],
    "es-ES": [
      "es"
    ],
    "es-US": [
      "us"
    ],
    "es-419": [
      "mx",
      "ar",
      "cl",
      "co",
      "pe"
    ],
    "fr-FR": [
      "fr"
    ],
    "fr-CA": [
      "ca"
    ],
    "pt-BR": [
      "br"
    ],
    "pt-PT": [
      "pt"
    ],
    "it-IT": [
      "it"
    ],
    "de-DE": [
      "de"
    ],
    "nl-NL": [
      "nl"
    ],
    "uk": [
      "ua"
    ],
    "pl-PL": [
      "pl"
    ],
    "tr-TR": [
      "tr"
    ],
    "ro": [
      "ro"
    ],
    "id": [
      "id"
    ],
    "fil": [
      "ph"
    ],
    "vi": [
      "vn"
    ],
    "zh-CN": [
      "cn"
    ],
    "zh-TW": [
      "tw"
    ],
    "ar": [
      "eg",
      "iq",
      "qa",
      "sa",
      "ae"
    ],
    "hi-IN": [
      "in"
    ],
    "ja-JP": [
      "jp"
    ],
    "hr": [
      "hr"
    ],
    "cs-CZ": [
      "cz"
    ],
    "da-DK": [
      "dk"
    ],
    "fi-FI": [
      "fi"
    ],
    "el-GR": [
      "gr"
    ],
    "iw-IL": [
      "il"
    ],
    "sv-SE": [
      "se"
    ],
    "sk": [
      "sk"
    ],
    "hu-HU": [
      "hu"
    ],
    "ca": [
      "es"
    ],
    "ko-KR": [
      "kr"
    ],
    "ms": [
      "my"
    ],
    "ms-MY": [
      "my"
    ],
    "th": [
      "th"
    ],
    "fa-AE": [
      "ae"
    ],
    "ne-NP": [
      "np"
    ],
    "mn-MN": [
      "mn"
    ],
    "mr-IN": [
      "in"
    ],
    "ml-IN": [
      "in"
    ],
    "mk-MK": [
      "mk"
    ],
    "lt": [
      "lt"
    ],
    "lv": [
      "lv"
    ],
    "lo-LA": [
      "la"
    ],
    "ky-KG": [
      "kg"
    ],
    "km-KH": [
      "kh"
    ],
    "kk": [
      "kz"
    ],
    "kn-IN": [
      "in"
    ],
    "is-IS": [
      "is"
    ],
    "gu": [
      "in"
    ],
    "ka-GE": [
      "ge"
    ],
    "gl-ES": [
      "es"
    ],
    "et": [
      "ee"
    ],
    "zh-HK": [
      "hk"
    ],
    "my-MM": [
      "mm"
    ],
    "bg": [
      "bg"
    ],
    "be": [
      "by"
    ],
    "eu-ES": [
      "es"
    ],
    "bn-BD": [
      "bd"
    ],
    "az-AZ": [
      "az"
    ],
    "hy-AM": [
      "am"
    ],
    "am": [
      "et"
    ],
    "sq": [
      "al"
    ],
    "af": [
      "za"
    ],
    "sr": [
      "rs"
    ],
    "sl": [
      "si"
    ]
  },
  "app_store": {
    "uk": [
      "ua"
    ],
    "ar-SA": [
      "sa"
    ],
    "ca": [
      "es"
    ],
    "zh-Hans": [
      "cn"
    ],
    "zh-Hant": [
      "tw",
      "hk"
    ],
    "hr": [
      "hr"
    ],
    "cs": [
      "cz"
    ],
    "da": [
      "dk"
    ],
    "nl-NL": [
      "nl"
    ],
    "en-AU": [
      "au"
    ],
    "en-CA": [
      "ca"
    ],
    "en-GB": [
      "gb"
    ],
    "en-US": [
      "us"
    ],
    "fi": [
      "fi"
    ],
    "fr-FR": [
      "fr"
    ],
    "fr-CA": [
      "ca"
    ],
    "de-DE": [
      "de"
    ],
    "el": [
      "gr"
    ],
    "he": [
      "il"
    ],
    "hi": [
      "in"
    ],
    "hu": [
      "hu"
    ],
    "id": [
      "id"
    ],
    "it": [
      "it"
    ],
    "ja": [
      "jp"
    ],
    "ko": [
      "kr"
    ],
    "ms": [
      "my"
    ],
    "no": [
      "no"
    ],
    "pl": [
      "pl"
    ],
    "pt-BR": [
      "br"
    ],
    "pt-PT": [
      "pt"
    ],
    "ro": [
      "ro"
    ],
    "sk": [
      "sk"
    ],
    "es-ES": [
      "es"
    ],
    "es-MX": [
      "mx"
    ],
    "sv": [
      "se"
    ],
    "th": [
      "th"
    ],
    "tr": [
      "tr"
    ],
    "vi": [
      "vn"
    ]
  }
}